Hermes/Beacon.py
Hermes/Client.py
Hermes/Config.py
Hermes/CoreCatalogService.py
Hermes/DBP.py
Hermes/LastCachedValue.py
Hermes/Logger.py
Hermes/Message.py
Hermes/Node.py
Hermes/Reactor.py
Hermes/Service.py
Hermes/Timer.py
Hermes/__init__.py
Hermes/main.py
Hermes/testing.py
Hermes/zhelpers.py
Hermes_lnestelroad-1.0.2.dist-info/LICENCE
Hermes_lnestelroad-1.0.2.dist-info/METADATA
Hermes_lnestelroad-1.0.2.dist-info/WHEEL
Hermes_lnestelroad-1.0.2.dist-info/top_level.txt
Hermes_lnestelroad-1.0.2.dist-info/RECORD
