Metadata-Version: 2.1
Name: Hermes-lnestelroad
Version: 1.0.2
Summary: A python message bus architecture with zeromq
Home-page: https://github.com/lnestelroad/Hermes
Author: Liam Nestelroad
Author-email: nestelroadliam@gmail.com
License: GPLv3+
Platform: UNKNOWN
Classifier: Programming Language :: Python :: 3
Classifier: License :: OSI Approved :: MIT License
Classifier: Operating System :: OS Independent
Requires-Dist: PyYAML
Requires-Dist: netifaces
Requires-Dist: pyzmq
